{
	"instance" : {
		"isObject" : "StefanMarr 4/2/2015 22:25",
		"isNumber" : "StefanMarr 4/2/2015 22:25",
		"asArray" : "StefanMarr 4/2/2015 22:26",
		"isBoolean" : "StefanMarr 4/2/2015 22:26",
		"isTrue" : "StefanMarr 4/2/2015 22:26",
		"isFalse" : "StefanMarr 4/2/2015 22:26",
		"isString" : "StefanMarr 4/2/2015 22:25",
		"isNull" : "StefanMarr 4/2/2015 22:26",
		"writeOn:" : "StefanMarr 4/2/2015 22:27",
		"asObject" : "StefanMarr 4/2/2015 22:26",
		"asBoolean" : "StefanMarr 4/2/2015 22:27",
		"isArray" : "StefanMarr 4/2/2015 22:25",
		"asDouble" : "StefanMarr 4/2/2015 22:26",
		"asInteger" : "StefanMarr 4/2/2015 22:26",
		"writeTo:" : "StefanMarr 4/2/2015 22:27",
		"asString" : "StefanMarr 4/2/2015 22:27"
	},
	"class" : {
		"string:" : "StefanMarr 4/2/2015 22:31",
		"integer:" : "StefanMarr 4/2/2015 22:28",
		"readFrom:" : "StefanMarr 4/2/2015 22:28",
		"cutOffPointZero:" : "StefanMarr 4/2/2015 22:32",
		"double:" : "StefanMarr 4/2/2015 22:30",
		"boolean:" : "StefanMarr 4/2/2015 22:31"
	}
}